{
  "kind": "singleType",
  "collectionName": "technologies",
  "info": {
    "singularName": "technology",
    "pluralName": "technologies",
    "displayName": "Технологии производства",
    "description": ""
  },
  "options": {
    "draftAndPublish": true
  },
  "attributes": {
    "title": {
      "type": "string",
      "required": true
    },
    "tabs": {
      "type": "component",
      "repeatable": true,
      "component": "technology.tab"
    },
    "seo": {
      "type": "component",
      "repeatable": false,
      "component": "shared.seo"
    }
  }
}
